{
    "purchases": [
        {
            "amount": 5,
            "id": 1,
            "name": "Banana Bunch",
            "price": 2.1
        },
        {
            "amount": 5,
            "id": 2,
            "name": "Jackfruit",
            "price": 5.5
        },
        {
            "amount": 5,
            "id": 7,
            "name": "Black Diamond Apple",
            "price": 30.87
        },
        {
            "amount": 5,
            "id": 4,
            "name": "IAC 'Honey Bud' Pineapple",
            "price": 20.77
        }
    ]
}
